arcor2/VERSION
arcor2/__init__.py
arcor2/cached.py
arcor2/docstring.py
arcor2/env.py
arcor2/flask.py
arcor2/helpers.py
arcor2/image.py
arcor2/json.py
arcor2/logging.py
arcor2/logic.py
arcor2/py.typed
arcor2/rest.py
arcor2/transformations.py
arcor2/urdf.py
arcor2/ws_server.py
arcor2/clients/__init__.py
arcor2/clients/aio_asset.py
arcor2/clients/aio_project_service.py
arcor2/clients/aio_scene_service.py
arcor2/clients/asset.py
arcor2/clients/project_service.py
arcor2/clients/scene_service.py
arcor2/data/__init__.py
arcor2/data/camera.py
arcor2/data/common.py
arcor2/data/events.py
arcor2/data/execution.py
arcor2/data/object_type.py
arcor2/data/robot.py
arcor2/data/scene.py
arcor2/data/rpc/__init__.py
arcor2/data/rpc/common.py
arcor2/exceptions/__init__.py
arcor2/exceptions/helpers.py
arcor2/object_types/__init__.py
arcor2/object_types/abstract.py
arcor2/object_types/flow_actions.py
arcor2/object_types/logic_actions.py
arcor2/object_types/random_actions.py
arcor2/object_types/time_actions.py
arcor2/object_types/upload.py
arcor2/object_types/utils.py
arcor2/parameter_plugins/__init__.py
arcor2/parameter_plugins/base.py
arcor2/parameter_plugins/boolean.py
arcor2/parameter_plugins/double.py
arcor2/parameter_plugins/image.py
arcor2/parameter_plugins/integer.py
arcor2/parameter_plugins/integer_enum.py
arcor2/parameter_plugins/joints.py
arcor2/parameter_plugins/list.py
arcor2/parameter_plugins/pose.py
arcor2/parameter_plugins/position.py
arcor2/parameter_plugins/string.py
arcor2/parameter_plugins/string_enum.py
arcor2/parameter_plugins/utils.py
arcor2/scripts/__init__.py
arcor2/scripts/upload_builtin_objects.py
arcor2/source/__init__.py
arcor2/source/utils.py
arcor2/test_objects/__init__.py
arcor2/test_objects/box.py
arcor2/test_objects/box2.py
arcor2/test_objects/dummy_multiarm_robot.py
arcor2/test_objects/param_to_return.py
arcor2/test_objects/position_param.py
arcor2/test_objects/tester.py
arcor2/test_objects/upload.py
arcor2-1.5.0.dist-info/METADATA
arcor2-1.5.0.dist-info/WHEEL
arcor2-1.5.0.dist-info/entry_points.txt
arcor2-1.5.0.dist-info/namespace_packages.txt
arcor2-1.5.0.dist-info/top_level.txt
arcor2-1.5.0.dist-info/RECORD
