Metadata-Version: 2.1
Name: arcor2
Version: 1.5.0
Summary: ARCOR2 base library
Author: Robo@FIT
Author-email: imaterna@fit.vut.cz
License: LGPL
Classifier: Development Status :: 3 - Alpha
Classifier: Intended Audience :: Developers
Classifier: Topic :: Software Development :: Build Tools
Classifier: License :: OSI Approved :: GNU Lesser General Public License v3 (LGPLv3)
Classifier: Programming Language :: Python :: 3.11
Classifier: Natural Language :: English
Classifier: Topic :: Scientific/Engineering
Requires-Python: ==3.11.*
Requires-Dist: Flask (~=3.0.3)
Requires-Dist: Pillow (~=10.3.0)
Requires-Dist: aiologger (~=0.7.0)
Requires-Dist: apispec-webframeworks (~=1.1.0)
Requires-Dist: apispec[yaml] (~=6.6.1)
Requires-Dist: autopep8 (~=2.2.0)
Requires-Dist: colorlog (~=6.8.2)
Requires-Dist: dataclasses-jsonschema[apispec,fast-dateparsing,fast-validation] (~=2.16.0)
Requires-Dist: fastuuid (~=0.8.0)
Requires-Dist: flask-swagger-ui (~=4.11.1)
Requires-Dist: flask-cors (~=4.0.1)
Requires-Dist: numpy-quaternion[numba,scipy] (~=2023.0.3)
Requires-Dist: numpy (~=1.26.4)
Requires-Dist: opencv-contrib-python (~=4.9.0.80)
Requires-Dist: orjson (~=3.10.3)
Requires-Dist: packaging (~=24.0)
Requires-Dist: pyhumps (==3.8.0)
Requires-Dist: python-dateutil (~=2.9.0.post0)
Requires-Dist: requests (~=2.32.3)
Requires-Dist: setuptools (~=70.0.0)
Requires-Dist: types-orjson (==3.6.2)
Requires-Dist: types-python-dateutil (==2.9.0.20240316)
Requires-Dist: types-requests (==2.32.0.20240602)
Requires-Dist: typing-inspect (~=0.9.0)
Requires-Dist: urdfpy (~=0.0.22)
Requires-Dist: websockets (~=12.0)
